setuptools_beehive.py
beehive/model_describe.py
beehive/step_registry.py
beehive/tag_expression.py
beehive/parser.py
beehive/model.py
beehive/runner.py
beehive/configuration.py
beehive/__main__.py
beehive/i18n.py
beehive/tag_matcher.py
beehive/matchers.py
beehive/json_parser.py
beehive/textutil.py
beehive/__init__.py
beehive/runner_util.py
beehive/log_capture.py
beehive/formatter/tags.py
beehive/formatter/html.py
beehive/formatter/filter_formatter.py
beehive/formatter/pretty.py
beehive/formatter/plain.py
beehive/formatter/ansi_escapes.py
beehive/formatter/sphinx_steps.py
beehive/formatter/base.py
beehive/formatter/formatters.py
beehive/formatter/rerun.py
beehive/formatter/json.py
beehive/formatter/filters.py
beehive/formatter/sphinx_util.py
beehive/formatter/__init__.py
beehive/formatter/progress.py
beehive/formatter/null.py
beehive/formatter/steps.py
beehive/compat/__init__.py
beehive/compat/collections.py
beehive/reporter/base.py
beehive/reporter/junit.py
beehive/reporter/__init__.py
beehive/reporter/summary.py
beehive-1.0.dist-info/entry_points.txt
beehive-1.0.dist-info/top_level.txt
beehive-1.0.dist-info/DESCRIPTION.rst
beehive-1.0.dist-info/WHEEL
beehive-1.0.dist-info/METADATA
beehive-1.0.dist-info/RECORD
beehive-1.0.dist-info/metadata.json
