Metadata-Version: 2.0
Name: beehive
Version: 1.0
Summary: beehive is behaviour-driven development, Python style
Home-page: http://github.com/vrutkovs/beehive
Author: Benno Rice, Richard Jones, Jens Engel, Vadim Rutkovsky
Author-email: roignac@gmail.com
License: BSD
Platform: UNKNOWN
Classifier: Development Status :: 4 - Beta
Classifier: Environment :: Console
Classifier: Intended Audience :: Developers
Classifier: Operating System :: OS Independent
Classifier: Programming Language :: Python :: 2.6
Classifier: Programming Language :: Python :: 2.7
Classifier: Programming Language :: Python :: 3.3
Classifier: Programming Language :: Python :: 3.4
Classifier: Programming Language :: Python :: Implementation :: CPython
Classifier: Programming Language :: Python :: Implementation :: Jython
Classifier: Programming Language :: Python :: Implementation :: PyPy
Classifier: Topic :: Software Development :: Testing
Classifier: License :: OSI Approved :: BSD License
Provides: beehive
Provides: setuptools_beehive
Requires-Dist: parse (>=1.6.3)
